{
  "product_id": "d525f1d6-42ff-4301-bb3b-480c82970ea0",
  "generated_at": "2025-12-03T02:27:47.654154",
  "physics_metrics": {
    "momentum": {
      "momentum7": -0.5195510002345943,
      "momentum14": -0.023977518422226722,
      "momentum30": -0.0694791307460436,
      "combined": -0.28086458179317386,
      "combined_momentum": -0.28086458179317386,
      "status": "FALLING"
    },
    "burst": {
      "actual": 1.0,
      "expected": 12.051213675213674,
      "burst_score": -1.4994528533806475,
      "level": "NORMAL",
      "burst_type": "NORMAL",
      "factors": {
        "baseline": 10.533333333333333,
        "dow": 0.9948717948717949,
        "payday": 1.15
      }
    },
    "priority_score": -0.19660520725522168
  },
  "recommendation": {
    "type": "INTERVENTION",
    "priority": "HIGH",
    "message": "Penjualan turun 28.1%. Perlu strategi baru.",
    "actions": [
      "Buat promo atau diskon terbatas",
      "Bundling dengan produk lain",
      "Tingkatkan aktivitas media sosial",
      "Cek kompetitor dan sesuaikan harga"
    ]
  }
}